main.py
functional_ai-0.1.0.dist-info/METADATA
functional_ai-0.1.0.dist-info/WHEEL
functional_ai-0.1.0.dist-info/top_level.txt
functional_ai-0.1.0.dist-info/RECORD
