Metadata-Version: 2.4
Name: functional-ai
Version: 0.1.0
Summary: Add your description here
Requires-Python: >=3.11
Requires-Dist: build>=1.2.2.post1
Requires-Dist: twine>=6.1.0
